{
  "id": "customradio",
  "name": "Custom Radio",
  "version": "3.3.2",
  "description": "Custom Radio lets you browse and play your own `.wav` music files directly from the `/RADIO` folder and nested directories (playlists), giving you full control over your playlist for wasteland adventures.",
  "icon": "assets/customradio.png",
  "tags": "media,system",
  "type": "app",
  "readme": "README.md",
  "custom": "",
  "storage": [
    { "name": "USER/customradio.js", "url": "app.min.js" },
    {
      "name": "USER/CUSTOM_RADIO/customradio.min.js",
      "url": "assets/customradio.min.js"
    }
  ]
}
